django_chime/__init__.py
django_chime/cli.py
django_chime/django_chime.py
tests/__init__.py
tests/test.py
django_chime-0.1.0.dist-info/AUTHORS.rst
django_chime-0.1.0.dist-info/LICENSE
django_chime-0.1.0.dist-info/METADATA
django_chime-0.1.0.dist-info/WHEEL
django_chime-0.1.0.dist-info/entry_points.txt
django_chime-0.1.0.dist-info/top_level.txt
django_chime-0.1.0.dist-info/RECORD
