Metadata-Version: 2.1
Name: django-chime
Version: 0.1.0
Summary: COVID-19 Hospital Impact Model for Epidemics (CHIME) app for Django.
Home-page: https://github.com/ChrisPappalardo/django-chime
Author: Chris Pappalardo
Author-email: cpappala@gmail.com
License: MIT license
Keywords: django-chime
Platform: UNKNOWN
Classifier: Development Status :: 2 - Pre-Alpha
Classifier: Intended Audience :: Developers
Classifier: License :: OSI Approved :: MIT License
Classifier: Natural Language :: English
Classifier: Programming Language :: Python :: 3
Classifier: Programming Language :: Python :: 3.7
Requires-Dist: click (>=6.0)
Requires-Dist: django (>=2.0)
Requires-Dist: djcorecap (>=1.0.1)
